mydatapreprocessing/__init__.py
mydatapreprocessing/consolidation/__init__.py
mydatapreprocessing/consolidation/consolidation_pipeline_internal.py
mydatapreprocessing/consolidation/consolidation_config/__init__.py
mydatapreprocessing/consolidation/consolidation_config/consolidation_config_internal.py
mydatapreprocessing/consolidation/consolidation_config/subconfigurations/__init__.py
mydatapreprocessing/consolidation/consolidation_config/subconfigurations/subconfigurations.py
mydatapreprocessing/consolidation/consolidation_functions/__init__.py
mydatapreprocessing/consolidation/consolidation_functions/consolidation_functions_internal.py
mydatapreprocessing/database/__init__.py
mydatapreprocessing/database/database_internal.py
mydatapreprocessing/datasets/__init__.py
mydatapreprocessing/datasets/datasets_internal.py
mydatapreprocessing/feature_engineering/__init__.py
mydatapreprocessing/feature_engineering/feature_engineering_internal.py
mydatapreprocessing/helpers/__init__.py
mydatapreprocessing/helpers/helpers_internal.py
mydatapreprocessing/load_data/__init__.py
mydatapreprocessing/load_data/load_data_internal.py
mydatapreprocessing/load_data/load_data_functions/__init__.py
mydatapreprocessing/load_data/load_data_functions/load_data_functions_internal.py
mydatapreprocessing/load_data/load_data_functions/data_parsers/__init__.py
mydatapreprocessing/load_data/load_data_functions/data_parsers/data_parsers_internal.py
mydatapreprocessing/misc/__init__.py
mydatapreprocessing/misc/misc_internal.py
mydatapreprocessing/preprocessing/__init__.py
mydatapreprocessing/preprocessing/preprocessing_pipeline_internal.py
mydatapreprocessing/preprocessing/inverse_preprocessing_config/__init__.py
mydatapreprocessing/preprocessing/inverse_preprocessing_config/inverse_preprocessing_config_internal.py
mydatapreprocessing/preprocessing/preprocessing_config/__init__.py
mydatapreprocessing/preprocessing/preprocessing_config/preprocessing_config_internal.py
mydatapreprocessing-3.0.3.dist-info/LICENSE
mydatapreprocessing-3.0.3.dist-info/METADATA
mydatapreprocessing-3.0.3.dist-info/WHEEL
mydatapreprocessing-3.0.3.dist-info/top_level.txt
mydatapreprocessing-3.0.3.dist-info/RECORD
