Metadata-Version: 2.1
Name: mydatapreprocessing
Version: 3.0.3
Summary: Library/framework for making predictions.
Home-page: https://github.com/Malachov/mydatapreprocessing
Author: Daniel Malachov
Author-email: malachovd@seznam.cz
License: mit
Platform: any
Classifier: Development Status :: 3 - Alpha
Classifier: Environment :: Other Environment
Classifier: Intended Audience :: Developers
Classifier: Intended Audience :: Education
Classifier: License :: OSI Approved :: MIT License
Classifier: Natural Language :: English
Classifier: Operating System :: OS Independent
Classifier: Programming Language :: Python :: 3.7
Classifier: Programming Language :: Python :: 3.9
Classifier: Programming Language :: Python :: 3.10
Classifier: Programming Language :: Python :: 3.11
Classifier: Programming Language :: Python
Classifier: Topic :: Software Development :: Libraries :: Application Frameworks
Classifier: Topic :: Software Development :: Libraries :: Python Modules
Requires-Python: >=3.7
License-File: LICENSE
Requires-Dist: mylogging (~=4.0.3)
Requires-Dist: mypythontools (~=3.0.2)
Requires-Dist: numpy
Requires-Dist: pandas
Requires-Dist: requests
Requires-Dist: scipy
Requires-Dist: sklearn
Requires-Dist: typing-extensions
Provides-Extra: all
Requires-Dist: wfdb ; extra == 'all'
Requires-Dist: openpyxl ; extra == 'all'
Requires-Dist: pyarrow ; extra == 'all'
Requires-Dist: pyodbc ; extra == 'all'
Requires-Dist: sqlalchemy ; extra == 'all'
Requires-Dist: tables ; extra == 'all'
Requires-Dist: xlrd ; extra == 'all'
Provides-Extra: datasets
Requires-Dist: wfdb ; extra == 'datasets'
Provides-Extra: datatypes
Requires-Dist: openpyxl ; extra == 'datatypes'
Requires-Dist: pyarrow ; extra == 'datatypes'
Requires-Dist: pyodbc ; extra == 'datatypes'
Requires-Dist: sqlalchemy ; extra == 'datatypes'
Requires-Dist: tables ; extra == 'datatypes'
Requires-Dist: xlrd ; extra == 'datatypes'
